upload/__init__.py
upload/main.py
upload-0.1.1.dist-info/DESCRIPTION.rst
upload-0.1.1.dist-info/METADATA
upload-0.1.1.dist-info/RECORD
upload-0.1.1.dist-info/WHEEL
upload-0.1.1.dist-info/entry_points.txt
upload-0.1.1.dist-info/metadata.json
upload-0.1.1.dist-info/top_level.txt
